torchrec/__init__.py
torchrec/streamable.py
torchrec/types.py
torchrec/datasets/__init__.py
torchrec/datasets/criteo.py
torchrec/datasets/movielens.py
torchrec/datasets/random.py
torchrec/datasets/utils.py
torchrec/datasets/scripts/__init__.py
torchrec/datasets/scripts/contiguous_preproc_criteo.py
torchrec/datasets/scripts/npy_preproc_criteo.py
torchrec/datasets/scripts/shuffle_preproc_criteo.py
torchrec/datasets/test_utils/__init__.py
torchrec/datasets/test_utils/criteo_test_utils.py
torchrec/distributed/__init__.py
torchrec/distributed/batched_embedding_kernel.py
torchrec/distributed/collective_utils.py
torchrec/distributed/comm.py
torchrec/distributed/comm_ops.py
torchrec/distributed/dist_data.py
torchrec/distributed/embedding.py
torchrec/distributed/embedding_kernel.py
torchrec/distributed/embedding_lookup.py
torchrec/distributed/embedding_sharding.py
torchrec/distributed/embedding_tower_sharding.py
torchrec/distributed/embedding_types.py
torchrec/distributed/embeddingbag.py
torchrec/distributed/fbgemm_qcomm_codec.py
torchrec/distributed/fused_embedding.py
torchrec/distributed/fused_embeddingbag.py
torchrec/distributed/grouped_position_weighted.py
torchrec/distributed/model_parallel.py
torchrec/distributed/quant_embedding.py
torchrec/distributed/quant_embedding_kernel.py
torchrec/distributed/quant_embeddingbag.py
torchrec/distributed/shard.py
torchrec/distributed/sharding_plan.py
torchrec/distributed/train_pipeline.py
torchrec/distributed/types.py
torchrec/distributed/utils.py
torchrec/distributed/composable/__init__.py
torchrec/distributed/composable/table_batched_embedding_slice.py
torchrec/distributed/planner/__init__.py
torchrec/distributed/planner/constants.py
torchrec/distributed/planner/enumerators.py
torchrec/distributed/planner/partitioners.py
torchrec/distributed/planner/perf_models.py
torchrec/distributed/planner/planners.py
torchrec/distributed/planner/proposers.py
torchrec/distributed/planner/shard_estimators.py
torchrec_nightly-2023.2.18.dist-info/LICENSE
torchrec_nightly-2023.2.18.dist-info/METADATA
torchrec_nightly-2023.2.18.dist-info/WHEEL
torchrec_nightly-2023.2.18.dist-info/top_level.txt
torchrec_nightly-2023.2.18.dist-info/RECORD
