Metadata-Version: 2.1
Name: torchrec-nightly
Version: 2023.2.18
Summary: Pytorch domain library for recommendation systems
Home-page: https://github.com/pytorch/torchrec
Author: TorchRec Team
Author-email: packages@pytorch.org
License: BSD-3
Keywords: pytorch,recommendation systems,sharding
Classifier: Development Status :: 4 - Beta
Classifier: Intended Audience :: Developers
Classifier: Intended Audience :: Science/Research
Classifier: License :: OSI Approved :: BSD License
Classifier: Programming Language :: Python :: 3
Classifier: Programming Language :: Python :: 3.7
Classifier: Topic :: Scientific/Engineering :: Artificial Intelligence
Requires-Python: >=3.7
License-File: LICENSE
Requires-Dist: fbgemm-gpu-nightly
Requires-Dist: iopath
Requires-Dist: pandas
Requires-Dist: tabulate
Requires-Dist: torchmetrics
Requires-Dist: tqdm
